bodkin/__init__.py
bodkin/core.py
bodkin/impl.py
bodkin/viz.py
bodkin/data/index.html.template
bodkin/data/script.js
bodkin/data/style.css
bodkin-0.1.1.dist-info/LICENSE
bodkin-0.1.1.dist-info/METADATA
bodkin-0.1.1.dist-info/WHEEL
bodkin-0.1.1.dist-info/top_level.txt
bodkin-0.1.1.dist-info/RECORD
