Metadata-Version: 2.1
Name: bodkin
Version: 0.1.1
Summary: Library to create and execute computation graphs
Home-page: https://gitlab.com/samflam/bodkin
Author: samflam
Author-email: bodkin@samflam.com
Classifier: Programming Language :: Python :: 3
Classifier: License :: OSI Approved :: MIT License
Classifier: Operating System :: OS Independent
Requires-Python: >=3.7
License-File: LICENSE
